README.md
setup.py
simple_ansible_api/__init__.py
simple_ansible_api/api.py
simple_ansible_api/callback.py
simple_ansible_api/task.py
simple_ansible_api.egg-info/PKG-INFO
simple_ansible_api.egg-info/SOURCES.txt
simple_ansible_api.egg-info/dependency_links.txt
simple_ansible_api.egg-info/not-zip-safe
simple_ansible_api.egg-info/requires.txt
simple_ansible_api.egg-info/top_level.txt