Metadata-Version: 2.1
Name: simple-ansible-api
Version: 1.3
Summary: This is a sample package
Home-page: https://github.com/towithyou/simple_ansible_api
Author: Haiquan
Author-email: haiquanduan@gmail.com
License: MIT
Keywords: ansible
Platform: UNKNOWN
Requires: ansible
